improv_ble_client/__init__.py
improv_ble_client/client.py
improv_ble_client/errors.py
improv_ble_client/models.py
improv_ble_client/protocol.py
improv_ble_client/py.typed
improv_ble_client/util.py
py_improv_ble_client-2.0.1.dist-info/licenses/LICENSE
py_improv_ble_client-2.0.1.dist-info/METADATA
py_improv_ble_client-2.0.1.dist-info/WHEEL
py_improv_ble_client-2.0.1.dist-info/top_level.txt
py_improv_ble_client-2.0.1.dist-info/zip-safe
py_improv_ble_client-2.0.1.dist-info/RECORD
