Metadata-Version: 2.4
Name: py-improv-ble-client
Version: 2.0.1
Summary: API to provision devices which implement Improv via BLE
License: MIT
Project-URL: Homepage, https://github.com/home-assistant-libs/py-improv-ble-client
Platform: any
Requires-Python: >=3.11.0
License-File: LICENSE
Dynamic: license-file
